ecosound/__init__.py
ecosound/_version.py
ecosound/classification/CrossValidation.py
ecosound/classification/__init__.py
ecosound/classification/classification.py
ecosound/core/__init__.py
ecosound/core/annotation.py
ecosound/core/audiotools.py
ecosound/core/decorators.py
ecosound/core/envelop.py
ecosound/core/measurement.py
ecosound/core/metadata.py
ecosound/core/spectrogram.py
ecosound/core/timestamp_formats.json
ecosound/core/tools.py
ecosound/datasets/__init__.py
ecosound/detection/__init__.py
ecosound/detection/blob_detector.py
ecosound/detection/detector_builder.py
ecosound/detection/detector_template.py
ecosound/detection/kurtosis_detector.py
ecosound/evaluation/__init__.py
ecosound/evaluation/prf.py
ecosound/localization/AnimationHPoptimization.py
ecosound/localization/ArrayOptimization.py
ecosound/localization/ArrayOptimization_plots.py
ecosound/localization/__init__.py
ecosound/localization/initial_tes.py
ecosound/localization/initial_tes_exeter.py
ecosound/localization/initial_tes_gridsearch.py
ecosound/localization/localization_batch_run.py
ecosound/localization/localizationlib.py
ecosound/localization/plotArrayUncertainties.py
ecosound/localization/plotArrayUncertainties_jen.py
ecosound/localization/plotArrayUncertainties_mobile_array.py
ecosound/localization/plot_localization_results.py
ecosound/localization/plot_localization_results_LArray_ROV.py
ecosound/localization/plot_localization_results_lingcod.py
ecosound/localization/plot_localization_results_lingcod_video.py
ecosound/localization/plot_localization_results_mini_ROV_video.py
ecosound/localization/plot_localization_results_mini_copper_video.py
ecosound/localization/plot_localization_results_mobile_copper2_video.py
ecosound/localization/plot_localization_results_mobile_copper_video.py
ecosound/localization/plot_localization_results_mobile_goby_video.py
ecosound/localization/plot_localization_results_mobile_projector.py
ecosound/localization/plot_localization_results_quillback.py
ecosound-0.0.31.dist-info/AUTHORS.rst
ecosound-0.0.31.dist-info/LICENSE
ecosound-0.0.31.dist-info/METADATA
ecosound-0.0.31.dist-info/WHEEL
ecosound-0.0.31.dist-info/top_level.txt
ecosound-0.0.31.dist-info/RECORD
