Metadata-Version: 2.1
Name: ecosound
Version: 0.0.31
Summary: Python toolkit for analysing passive acoustic data
Home-page: https://github.com/xaviermouy/ecosound
Author: Xavier Mouy
Author-email: xaviermouy@uvic.ca
License: BSD license
Keywords: ecosound
Classifier: Development Status :: 3 - Alpha
Classifier: Intended Audience :: Developers
Classifier: Programming Language :: Python :: 3
Classifier: Programming Language :: Python :: 3.5
Classifier: Programming Language :: Python :: 3.6
Classifier: Programming Language :: Python :: 3.7
Classifier: Programming Language :: Python :: 3.8
Classifier: Programming Language :: Python :: 3.9
Classifier: License :: OSI Approved :: BSD License
Classifier: Operating System :: OS Independent
Classifier: Natural Language :: English
Requires-Python: >=3.6.0
License-File: LICENSE
License-File: AUTHORS.rst
Requires-Dist: xarray[complete]
Requires-Dist: dask[complete]
Requires-Dist: pandas
Requires-Dist: numba
Requires-Dist: dask-image
Requires-Dist: matplotlib
Requires-Dist: ipympl
Requires-Dist: scipy
Requires-Dist: numpy
Requires-Dist: scikit-learn
Requires-Dist: toolz
Requires-Dist: opencv-python >=4.5.5.64
Requires-Dist: soundfile >=0.10.0
Requires-Dist: netCDF4
Requires-Dist: tqdm
Requires-Dist: eccodes ==1.2.0
